gmtrade-3.0.6.data/purelib/gmtrade-3.0.6-py3.9-nspkg.pth
gmtrade-3.0.6.data/purelib/gmtrade/__version__.py
gmtrade-3.0.6.data/purelib/gmtrade/constant.py
gmtrade-3.0.6.data/purelib/gmtrade/enum.py
gmtrade-3.0.6.data/purelib/gmtrade/pb_to_dict.py
gmtrade-3.0.6.data/purelib/gmtrade/retrying.py
gmtrade-3.0.6.data/purelib/gmtrade/utils.py
gmtrade-3.0.6.data/purelib/gmtrade/api/__init__.py
gmtrade-3.0.6.data/purelib/gmtrade/api/callback.py
gmtrade-3.0.6.data/purelib/gmtrade/api/storage.py
gmtrade-3.0.6.data/purelib/gmtrade/api/trade.py
gmtrade-3.0.6.data/purelib/gmtrade/csdk/__init__.py
gmtrade-3.0.6.data/purelib/gmtrade/csdk/c_sdk.cpython-39-x86_64-linux-gnu.so
gmtrade-3.0.6.data/purelib/gmtrade/csdk/libgmtrade.so
gmtrade-3.0.6.data/purelib/gmtrade/csdk/setup.py
gmtrade-3.0.6.data/purelib/gmtrade/csdk/setup_linux.py
gmtrade-3.0.6.data/purelib/gmtrade/pb/__init__.py
gmtrade-3.0.6.data/purelib/gmtrade/pb/account_pb2.py
gmtrade-3.0.6.data/purelib/gmtrade/pb/common_pb2.py
gmtrade-3.0.6.data/purelib/gmtrade/pb/performance_pb2.py
gmtrade-3.0.6.data/purelib/gmtrade/pb/trade_pb2.py
gmtrade-3.0.6.dist-info/METADATA
gmtrade-3.0.6.dist-info/WHEEL
gmtrade-3.0.6.dist-info/namespace_packages.txt
gmtrade-3.0.6.dist-info/top_level.txt
gmtrade-3.0.6.dist-info/RECORD
