Metadata-Version: 2.1
Name: gmtrade
Version: 3.0.6
Summary: 掘金量化 掘金3 交易sdk
Home-page: http://myquant.cn/
Author: myquant_dev
Author-email: support@myquant.cn
License: Apache 2.0
Classifier: Programming Language :: Python :: 3.6
Classifier: Programming Language :: Python :: 3.7
Classifier: Programming Language :: Python :: 3.8
Classifier: Programming Language :: Python :: 3.9
Classifier: Programming Language :: Python :: 3.10
Requires-Python: >=3.6, <4
Requires-Dist: python-dateutil (>=2.7.3)
Requires-Dist: arrow (>=0.12.1)
Requires-Dist: grpcio (>=1.17.1)
Requires-Dist: Cython (>=0.26.1)
Requires-Dist: protobuf (<4.0,>=3.6.0)
Requires-Dist: attrs (>=18.1.0)
